{
    "Nascimento": "Gerhart Hirsch9 de fevereiro de 1923Viena",
    "Morte": "22 de setembro de 2007 (84 anos)Vosnon",
    "Cidadania": "França, Áustria",
    "Alma mater": [
        "Escola Politécnica Federal de Lausana",
        "Lyceum Alpinum Zuoz"
    ],
    "Ocupação": "economista,jornalista,filósofo,escritor,sociólogo,ambientalista, cientista político, jornalista de opinião",
    "Empregador(a)": "Le Nouvel Observateur,L'Express,Les Temps modernes",
    "Obras destacadas": "Paths to Paradise: On the Liberation from Work",
    "Movimento estético": "ecologismo,decrescimento"
}