{
    "Nascimento": "29 de janeiro de 1904Leipzig",
    "Morte": "30 de janeiro de 1976 (72 anos)Hamburgo",
    "Sepultamento": "Friedhof Göggingen",
    "Cidadania": "Alemanha",
    "Progenitores": [
        "Max Gehlen"
    ],
    "Alma mater": [
        "Universidade de Leipzig",
        "Thomasschule zu Leipzig"
    ],
    "Ocupação": "antropólogo,sociólogo,filósofo",
    "Empregador(a)": "Universidade de Viena,Universidade de Leipzig,Universidade Técnica da Renânia do Norte-Vestfália em Aachen,Universidade de Frankfurt",
    "Movimento estético": "antropologia filosófica"
}