{
    "Capital": "Camberra35°18'S 149°08'E",
    "Maior cidade": "•Sydney(metropolitana)•Melbourne(urbana)",
    "Língua oficial": "Inglês(de facto)N1",
    "Gentílico": "australiano(a)",
    "Governo": "Monarquia constitucionaledemocraciafederalparlamentar",
    "•Monarca": "Carlos III",
    "•Governador-geral": "Sam Mostyn",
    "•Primeiro-ministro": "Anthony Albanese",
    "•Presidente do Supremo Tribunal": "Robert French",
    "•Constituição": "1 de janeirode1901",
    "•Estatuto de Westminster": "11 de dezembrode1931",
    "•Acto de adopção do Estatuto de Westminster": "9 de outubrode1942(efectivamente em3 de setembrode1939)",
    "•Acto da Austrália": "3 de marçode1986",
    "• Total": "US$1,790trilhão*[4](13.º)",
    "• Água (%)": "1",
    "• Estimativa para 2024": "27 195 388[2]hab. (53.º)",
    "• Censo 2021": "25 890 773[3]hab.",
    "•Densidade": "3,5 hab./km² (235.º)",
    "PIB(basePPC)": "Estimativa para 2023",
    "•Per capita": "US$ 66 589[4](5.º)",
    "IDH(2021)": "0,951 (5.º) –muito alto[5]",
    "Moeda": "Dólar australiano(AUD)",
    "Fuso horário": "Vários",
    "• Verão (DST)": "Vários",
    "Cód. ISO": "AUS",
    "Cód. Internet": ".au",
    "Cód. telef.": "+61",
    "Websitegovernamental": "www.australia.gov.au"
}