{
    "Nascimento": "26 de julhode1933(91 anos)Evanston",
    "Nacionalidade": "estadunidense",
    "Cidadania": "Estados Unidos",
    "Alma mater": "Universidade Yale,Amherst College",
    "Ocupação": "economista,professor universitário",
    "Distinções": "Nobel de Economia(2006)",
    "Empregador(a)": "Universidade Columbia,Universidade da Pensilvânia",
    "Orientador(a)(es/s)": "William Fellner,James Tobin",
    "Instituições": "Universidade Columbia,Universidade da Pensilvânia",
    "Campo(s)": "economia"
}