{
    "Período": "15 de novembrode1906a15 de novembrode1909",
    "Vice-presidente": "Nenhum",
    "Antecessor(a)": "Afonso Pena",
    "Sucessor(a)": "Venceslau Brás",
    "Nome completo": "Nilo Procópio Peçanha",
    "Nascimento": "2 de outubrode1867Campos dos Goytacazes,Rio de Janeiro,Império do Brasil",
    "Morte": "31 de marçode1924(56 anos)Rio de Janeiro,Distrito Federal",
    "Alma mater": "Faculdade de Direito do Recife",
    "Cônjuge": "Ana de Sousa(1895–1924)",
    "Filhos(as)": "Nilo, Zulma e Mário",
    "Partido": "Republicano Fluminense",
    "Profissão": "Advogado",
    "Assinatura": ""
}