{
    "Presidente": "Anton Drexler(1920-1921)Adolf Hitler(comoFührer)(1921-1945)Martin Bormann(comoMinistro do Partido)(1945)",
    "Fundador": "Anton Drexler",
    "Fundação": "1920",
    "Dissolução": "1945",
    "Sede": "Munique,Alemanha[1]",
    "Ideologia": "Nacional-socialismo(Nazismo)Racismo científicoPangermanismoAnticomunismoAntissemitismoMilitarismo",
    "Espectro político": "extrema-direita[2][3]",
    "Publicação": "Völkischer Beobachter",
    "Ala de estudantes": "Liga dos Estudantes Alemães Nacional-Socialistas",
    "Ala de juventude": [
        "Deutsches Jungvolk(DJ)",
        "Liga das Moças Alemãs(BDM)"
    ],
    "Ala feminina": "Liga das Mulheres Nacional-Socialistas",
    "Antecessor": "Partido dos Trabalhadores Alemães",
    "Sucessor": "Nenhum(banido)Suas ideologias prosseguiram com oneo-nazismo",
    "Membros": [
        "Menos de 60, em 1920",
        "8,5 milhões, em 1945[4]"
    ],
    "Cores": "VermelhoPretoBrancoMarrom",
    "Slogan": "Ein Volk, ein Reich, ein Führer(não oficial)"
}